hyfiml/__cli__.py
hyfiml/__init__.py
hyfiml/_version.py
hyfiml/conf/__init__.py
hyfiml/conf/about/hyfiml.yaml
hyfiml/models/__init__.py
hyfiml/models/text_classifier.py
hyfiml/py.typed
hyfi_ml-0.2.0.dist-info/LICENSE
hyfi_ml-0.2.0.dist-info/METADATA
hyfi_ml-0.2.0.dist-info/WHEEL
hyfi_ml-0.2.0.dist-info/entry_points.txt
hyfi_ml-0.2.0.dist-info/RECORD
