Metadata-Version: 2.1
Name: hyfi-ml
Version: 0.2.0
Summary: HyFI-ML is a Python package that extends the Hydra Fast Interface (HyFI) framework with machine learning capabilities.
Home-page: https://hyfi-ml.entelecheia.ai
License: MIT
Author: Young Joon Lee
Author-email: entelecheia@hotmail.com
Requires-Python: >=3.9,<3.13
Classifier: License :: OSI Approved :: MIT License
Classifier: Programming Language :: Python :: 3
Classifier: Programming Language :: Python :: 3.9
Classifier: Programming Language :: Python :: 3.10
Classifier: Programming Language :: Python :: 3.11
Classifier: Programming Language :: Python :: 3.12
Requires-Dist: cleanlab (>=2.0.0,<=2.6.3)
Requires-Dist: click (>=8.1.3,<9.0.0)
Requires-Dist: evaluate (>=0.4.0,<=0.4.1)
Requires-Dist: hyfi (>=1.36.3,<2.0.0)
Requires-Dist: scikit-learn (>=1.0.0,<=1.4.1.post1)
Requires-Dist: transformers[torch] (>=4.0.0,<=4.39.1)
Project-URL: Repository, https://github.com/entelecheia/hyfi-ml
